neattext/__init__.py
neattext/explainer/__init__.py
neattext/explainer/explainer.py
neattext/functions/Emoji_Sentiment_Data.csv
neattext/functions/__init__.py
neattext/functions/emoji.json
neattext/functions/functions.py
neattext/neattext.py
neattext/pattern_data/__init__.py
neattext/pattern_data/pattern_data.py
neattext/pattern_data/stopwords_list.py
neattext-0.1.1.dist-info/LICENSE
neattext-0.1.1.dist-info/WHEEL
neattext-0.1.1.dist-info/METADATA
neattext-0.1.1.dist-info/RECORD
