Metadata-Version: 2.1
Name: neattext
Version: 0.1.1
Summary: Neattext - a simple NLP package for cleaning text
Home-page: https://github.com/Jcharis/neattext
License: MIT
Keywords: neattext,tidytext,jcharistech,clean text,NLP,text preprocessing,text cleaning,ftfy,pandas,normalize
Author: Jesse E.Agbe(JCharis)
Author-email: jcharistech@gmail.com
Requires-Python: >=3.3,<4.0
Classifier: License :: OSI Approved :: MIT License
Classifier: Operating System :: OS Independent
Classifier: Programming Language :: Python :: 3
Classifier: Programming Language :: Python :: 3.4
Classifier: Programming Language :: Python :: 3.5
Classifier: Programming Language :: Python :: 3.6
Classifier: Programming Language :: Python :: 3.7
Classifier: Programming Language :: Python :: 3.8
Classifier: Programming Language :: Python :: 3.9
Project-URL: Repository, https://github.com/Jcharis/neattext
